KratosMultiphysics/CoSimulationApplication/MainKratosCoSim.py
KratosMultiphysics/CoSimulationApplication/__init__.py
KratosMultiphysics/CoSimulationApplication/analysis_stage_with_co_sim_io.py
KratosMultiphysics/CoSimulationApplication/co_simulation_analysis.py
KratosMultiphysics/CoSimulationApplication/co_simulation_tools.py
KratosMultiphysics/CoSimulationApplication/colors.py
KratosMultiphysics/CoSimulationApplication/coupling_interface_data.py
KratosMultiphysics/CoSimulationApplication/empire_wrapper.py
KratosMultiphysics/CoSimulationApplication/fluid_dynamics_analysis_with_co_sim_io.py
KratosMultiphysics/CoSimulationApplication/function_callback_utility.py
KratosMultiphysics/CoSimulationApplication/structural_mechanics_analysis_with_co_sim_io.py
KratosMultiphysics/CoSimulationApplication/base_classes/__init__.py
KratosMultiphysics/CoSimulationApplication/base_classes/co_simulation_convergence_accelerator.py
KratosMultiphysics/CoSimulationApplication/base_classes/co_simulation_convergence_criteria.py
KratosMultiphysics/CoSimulationApplication/base_classes/co_simulation_coupled_solver.py
KratosMultiphysics/CoSimulationApplication/base_classes/co_simulation_coupling_operation.py
KratosMultiphysics/CoSimulationApplication/base_classes/co_simulation_data_transfer_operator.py
KratosMultiphysics/CoSimulationApplication/base_classes/co_simulation_io.py
KratosMultiphysics/CoSimulationApplication/base_classes/co_simulation_predictor.py
KratosMultiphysics/CoSimulationApplication/base_classes/co_simulation_solver_wrapper.py
KratosMultiphysics/CoSimulationApplication/convergence_accelerators/__init__.py
KratosMultiphysics/CoSimulationApplication/convergence_accelerators/aitken.py
KratosMultiphysics/CoSimulationApplication/convergence_accelerators/anderson.py
KratosMultiphysics/CoSimulationApplication/convergence_accelerators/block_ibqnls.py
KratosMultiphysics/CoSimulationApplication/convergence_accelerators/block_mvqn.py
kratoscosimulationapplication-10.4.0.dist-info/METADATA
kratoscosimulationapplication-10.4.0.dist-info/WHEEL
kratoscosimulationapplication-10.4.0.dist-info/RECORD
